pixie.cpython-36m-x86_64-linux-gnu.so
slime.cpython-36m-x86_64-linux-gnu.so
peqnp/__init__.py
peqnp/entity.py
peqnp/gaussian.py
peqnp/linear.py
peqnp/rational.py
peqnp/solver.py
peqnp/stdlib.py
PEQNP-5.2.3.dist-info/LICENSE
PEQNP-5.2.3.dist-info/METADATA
PEQNP-5.2.3.dist-info/WHEEL
PEQNP-5.2.3.dist-info/top_level.txt
PEQNP-5.2.3.dist-info/RECORD
