Metadata-Version: 2.1
Name: PEQNP
Version: 5.2.3
Summary: PEQNP Mathematical Solver from http://www.peqnp.com
Home-page: http://www.peqnp.com
Author: Oscar Riveros
Author-email: contact@peqnp.science
License: copyright (c) 2012-2020 Oscar Riveros. All rights reserved.
Keywords: csp,mip
Platform: UNKNOWN
